Metadata-Version: 1.1
Name: django-logon-testcase
Version: 0.1.0
Summary: Simple enhancement to the TestCase which creates user and loggs him in.
Home-page: https://github.com/petr.dlouhy/django-logon-testcase
Author: Petr Dlouhý
Author-email: petr.dlouhy@email.cz
License: MIT
Keywords: django-logon-testcase
Platform: UNKNOWN
Classifier: Development Status :: 3 - Alpha
Classifier: Framework :: Django
Classifier: Framework :: Django :: 1.8
Classifier: Framework :: Django :: 1.9
Classifier: Framework :: Django :: 1.10
Classifier: Intended Audience :: Developers
Classifier: License :: OSI Approved :: BSD License
Classifier: Natural Language :: English
Classifier: Programming Language :: Python :: 2
Classifier: Programming Language :: Python :: 2.7
Classifier: Programming Language :: Python :: 3
Classifier: Programming Language :: Python :: 3.3
Classifier: Programming Language :: Python :: 3.4
Classifier: Programming Language :: Python :: 3.5
